weixinpay/__init__.py
weixinpay/wxpay.py
weixinpay-0.1.1.dist-info/top_level.txt
weixinpay-0.1.1.dist-info/WHEEL
weixinpay-0.1.1.dist-info/RECORD
weixinpay-0.1.1.dist-info/METADATA
weixinpay-0.1.1.dist-info/metadata.json
weixinpay-0.1.1.dist-info/DESCRIPTION.rst
